rmr/__init__.py
rmr/exceptions.py
rmr/helpers.py
rmr/rmr.py
rmr/rmr_mocks/__init__.py
rmr/rmr_mocks/rmr_mocks.py
rmr-4.0.0.data/data/LICENSE.txt
rmr-4.0.0.dist-info/LICENSE.txt
rmr-4.0.0.dist-info/METADATA
rmr-4.0.0.dist-info/WHEEL
rmr-4.0.0.dist-info/top_level.txt
rmr-4.0.0.dist-info/RECORD
