Metadata-Version: 2.1
Name: rmr
Version: 4.0.0
Summary: Python wrapper for RIC RMR
Home-page: https://gerrit.o-ran-sc.org/r/admin/repos/ric-plt/lib/rmr
Author: Tommy Carpenter, E. Scott Daniels
License: Apache 2.0
Keywords: RIC rmr
Platform: UNKNOWN
Classifier: Development Status :: 4 - Beta
Classifier: Intended Audience :: Telecommunications Industry
Classifier: Programming Language :: Python :: 3
Classifier: Programming Language :: Python :: 3.7
Classifier: License :: OSI Approved :: Apache Software License
Classifier: Operating System :: POSIX :: Linux
Classifier: Topic :: Communications
Requires-Python: >=3.7
